assignment_2/Q2/a/s_box.v
`timescale 1ps/1ps

module s_box(
    input [3:0] x, 
    output reg [3:0] sx
    );

    always@(x) begin
        case(x)
            4'h0: sx <= 4'hC;
            4'h1: sx <= 4'h5;
            4'h2: sx <= 4'h6;
            4'h3: sx <= 4'hB;
            4'h4: sx <= 4'h9;
            4'h5: sx <= 4'h0;
            4'h6: sx <= 4'hA;
            4'h7: sx <= 4'hD;
            4'h8: sx <= 4'h3;
            4'h9: sx <= 4'hE;
            4'hA: sx <= 4'hF;
            4'hB: sx <= 4'h8;
            4'hC: sx <= 4'h4;
            4'hD: sx <= 4'h7;
            4'hE: sx <= 4'h1;
            4'hF: sx <= 4'h2;
            default sx <= 4'h0;
        endcase
    end
    
endmodule

assignment_2/Q2/a/s_box_test.v
`timescale 1ps/1ps
`include "s_box.v"

module s_box_test;
    reg [3:0] in;
    wire [3:0] out;

    s_box uut(in, out);

    initial begin
        $dumpfile("waveform.vcd");
        $dumpvars(0,s_box_test);
        
        in = 4'h0;
    end

    initial $monitor(" s = %h | s[x] = %h", in, out);
    always #5 in=in+1'h1;
    initial #75 $finish;
    
endmodule

assignment_2/Q2/a/waveform.vcd
$date
	Mon Aug 29 21:48:35 2022
$end
$version
	Icarus Verilog
$end
$timescale
	1ps
$end
$scope module s_box_test $end
$var wire 4 ! out [3:0] $end
$var reg 4 " in [3:0] $end
$scope module uut $end
$var wire 4 # x [3:0] $end
$var reg 4 $ sx [3:0] $end
$upscope $end
$upscope $end
$enddefinitions $end
#0
$dumpvars
b1100 $
b0 #
b0 "
b1100 !
$end
#5
b101 !
b101 $
b1 "
b1 #
#10
b110 !
b110 $
b10 "
b10 #
#15
b1011 !
b1011 $
b11 "
b11 #
#20
b1001 !
b1001 $
b100 "
b100 #
#25
b0 !
b0 $
b101 "
b101 #
#30
b1010 !
b1010 $
b110 "
b110 #
#35
b1101 !
b1101 $
b111 "
b111 #
#40
b11 !
b11 $
b1000 "
b1000 #
#45
b1110 !
b1110 $
b1001 "
b1001 #
#50
b1111 !
b1111 $
b1010 "
b1010 #
#55
b1000 !
b1000 $
b1011 "
b1011 #
#60
b100 !
b100 $
b1100 "
b1100 #
#65
b111 !
b111 $
b1101 "
b1101 #
#70
b1 !
b1 $
b1110 "
b1110 #
#75
b10 !
b10 $
b1111 "
b1111 #
