assignment_2/Q2/b/s_box.v
`timescale 1ps/1ps

module s_box(
    input [3:0] x, 
    output [3:0] sx
    );

    assign sx[3] = (!x[3] & !x[1] & !x[0]) |
                   (!x[3] & x[1] & x[0]) |
                   (!x[3] & x[2] & !x[0]) |
                   (x[3] & !x[2] & x[0]) | 
                   (x[3] & !x[2] & x[1]);

    assign sx[2] = (!x[3] & !x[2] & !x[1]) | 
                   (!x[2] & !x[1] & x[0]) |
                   (!x[2] & x[1] & !x[0]) |
                   (x[3] & x[2] & !x[1]) |
                   (!x[3] & x[2] & x[1] & x[0]);
    
    assign sx[1] = (!x[3] & !x[2] & x[1]) | 
                   (!x[3] & x[1] & !x[0]) |
                   (!x[2] & x[1] & !x[0]) | 
                   (x[3] & !x[2] & !x[1]) |
                   (x[3] & x[2] & x[0]);

    assign sx[0] = (!x[3] & !x[2] & x[0]) |
                   (!x[3] & x[1] & x[0]) | 
                   (x[3] & !x[2] & !x[0]) |
                   (x[3] & x[2] & !x[0]) |
                   (!x[3] & x[2] & !x[1] & !x[0]) | 
                   (x[3] & x[2] & !x[1] & x[0]);

endmodule

assignment_2/Q2/b/s_box_test.v
`timescale 1ps/1ps
`include "s_box.v"

module s_box_test;
    reg [3:0] in;
    wire [3:0] out;

    s_box uut(in, out);

    initial begin
        $dumpfile("waveform.vcd");
        $dumpvars(0,s_box_test);

        in = 4'h0;
    end


    initial $monitor(" s = %h | s[x] = %h", in, out);
    always #5 in=in+1'h1;
    initial #75 $finish;
    
endmodule

assignment_2/Q2/b/waveform.vcd
$date
	Sun Sep  4 02:52:19 2022
$end
$version
	Icarus Verilog
$end
$timescale
	1ps
$end
$scope module s_box_test $end
$var wire 4 ! out [3:0] $end
$var reg 4 " in [3:0] $end
$scope module uut $end
$var wire 4 # x [3:0] $end
$var wire 4 $ sx [3:0] $end
$upscope $end
$upscope $end
$enddefinitions $end
#0
$dumpvars
b1100 $
b0 #
b0 "
b1100 !
$end
#5
b101 !
b101 $
b1 "
b1 #
#10
b110 !
b110 $
b10 "
b10 #
#15
b1011 !
b1011 $
b11 "
b11 #
#20
b1001 !
b1001 $
b100 "
b100 #
#25
b0 !
b0 $
b101 "
b101 #
#30
b1010 !
b1010 $
b110 "
b110 #
#35
b1101 !
b1101 $
b111 "
b111 #
#40
b11 !
b11 $
b1000 "
b1000 #
#45
b1110 !
b1110 $
b1001 "
b1001 #
#50
b1111 !
b1111 $
b1010 "
b1010 #
#55
b1000 !
b1000 $
b1011 "
b1011 #
#60
b101 !
b101 $
b1100 "
b1100 #
#65
b111 !
b111 $
b1101 "
b1101 #
#70
b1 !
b1 $
b1110 "
b1110 #
#75
b10 !
b10 $
b1111 "
b1111 #
