7_DFF/dff.v
`timescale 1ps/1ps

module dff (
    output reg q, qbar,
    input d, clk, clear
);
    always @(posedge clk or negedge clear) begin
        if (clear==1'b0)
            begin q<=1'b0; qbar<=1'b1; end
        else 
            begin q<=d; qbar<=~d; end
    end
    
endmodule

7_DFF/dff_test.v
`timescale 1ps/1ps
`include "dff.v"

module dff_test;
    reg d;
    reg clk;
    reg clear;

    wire q;
    wire qbar;

    dff uut(
        .q(q),
        .qbar(qbar),
        .d(d),
        .clk(clk),
        .clear(clear)
    );

    initial begin
        $dumpfile("waveform.vcd");
        $dumpvars(0,dff_test);

        d=1'b0;
        clk=1'b0;
        clear=1'b1;
    end

    always #10 d=d+1'b1;
    initial #90 clear=1'b0;
    always #3 clk=!clk;

    initial $monitor($time," d=%b, clk=%b, clear=%b | q=%b, qbar=%b",d,clk,clear,q,qbar);
    initial #100 $finish;

endmodule

7_DFF/waveform.vcd
$date
	Mon Aug 15 17:27:12 2022
$end
$version
	Icarus Verilog
$end
$timescale
	1ps
$end
$scope module dff_test $end
$var wire 1 ! qbar $end
$var wire 1 " q $end
$var reg 1 # clear $end
$var reg 1 $ clk $end
$var reg 1 % d $end
$scope module uut $end
$var wire 1 # clear $end
$var wire 1 $ clk $end
$var wire 1 % d $end
$var reg 1 " q $end
$var reg 1 ! qbar $end
$upscope $end
$upscope $end
$enddefinitions $end
#0
$dumpvars
0%
0$
1#
x"
x!
$end
#3
1!
0"
1$
#6
0$
#9
1$
#10
1%
#12
0$
#15
0!
1"
1$
#18
0$
#20
0%
#21
1!
0"
1$
#24
0$
#27
1$
#30
0$
1%
#33
0!
1"
1$
#36
0$
#39
1$
#40
0%
#42
0$
#45
1!
0"
1$
#48
0$
#50
1%
#51
0!
1"
1$
#54
0$
#57
1$
#60
0$
0%
#63
1!
0"
1$
#66
0$
#69
1$
#70
1%
#72
0$
#75
0!
1"
1$
#78
0$
#80
0%
#81
1!
0"
1$
#84
0$
#87
1$
#90
0$
1%
0#
#93
1$
#96
0$
#99
1$
#100
0%
