2_full_adder/dataflow/full_adder.v
`timescale 1ps/1ps

module full_adder (
    output s,co,
    input a,b,c
);
    assign s = a^b^c;
    assign co = (a&b)|(b&c)|(a&c);
endmodule

2_full_adder/dataflow/full_adder_test.v
`timescale 1ps/1ps
`include "full_adder.v"

module full_adder_test;
    reg a;
    reg b;
    reg c;

    wire s;
    wire co;

    full_adder uut (
        .s(s),
        .co(co),
        .a(a),
        .b(b),
        .c(c)
    );

    initial begin
        $dumpfile("waveform.vcd");
        $dumpvars(0,full_adder_test);
        
        {a,b,c} =3'b000; 
        #2 {a,b,c} =3'b001;
        #2 {a,b,c} =3'b010;
        #2 {a,b,c} =3'b011;
        #2 {a,b,c} =3'b100;
        #2 {a,b,c} =3'b101;
        #2 {a,b,c} =3'b110;
        #2 {a,b,c} =3'b111; 
    end

    initial $monitor("a=%b,b=%b,c=%b,s=%b,co=%b",a,b,c,s,co);
    initial #20 $finish;
    
endmodule

full_adder/dataflow/waveform.vcd
$date
	Sun Aug 14 13:05:22 2022
$end
$version
	Icarus Verilog
$end
$timescale
	1ps
$end
$scope module full_adder_test $end
$var wire 1 ! s $end
$var wire 1 " co $end
$var reg 1 # a $end
$var reg 1 $ b $end
$var reg 1 % c $end
$scope module uut $end
$var wire 1 # a $end
$var wire 1 $ b $end
$var wire 1 % c $end
$var wire 1 " co $end
$var wire 1 ! s $end
$upscope $end
$upscope $end
$enddefinitions $end
#0
$dumpvars
0%
0$
0#
0"
0!
$end
#2
1!
1%
#4
1!
1$
0%
#6
1"
0!
1%
#8
0"
1!
1#
0$
0%
#10
1"
0!
1%
#12
1"
0!
1$
0%
#14
1!
1%
