2_full_adder/dataflow/full_adder.v
`timescale 1ps/1ps

module full_adder (
    output s,co,
    input a,b,c
);
    assign s = a^b^c;
    assign co = (a&b)|(b&c)|(a&c);
endmodule

6_adder_4bit/adder.v
`timescale 1ps/1ps
`include "full_adder.v"

module adder (s,co,a,b,ci);
    output [3:0]s;
    output co;

    wire [2:0] c;

    input [3:0] a,b;
    input ci;

    full_adder add1(s[0],c[0],a[0],b[0],ci);
    full_adder add2(s[1],c[1],a[1],b[1],c[0]);
    full_adder add3(s[2],c[2],a[2],b[2],c[1]);
    full_adder add4(s[3],co,a[3],b[3],c[2]);

endmodule

6_adder_4bit/adder_test.v
`timescale 1ps/1ps
`include "adder.v"

module adder_test;
    reg[3:0] a;
    reg[3:0] b;
    reg ci;

    wire[3:0] s;
    wire co;

    adder uut(
        .s(s),
        .co(co),
        .a(a),
        .b(b),
        .ci(ci)
    );

    initial begin
        $dumpfile("waveform.vcd");
        $dumpvars(0,adder_test);
        
        a = 4'b0000;
        b = 4'b0000;
        ci = 0;
    end

    always #1 b = b+1'b1;
    always #2 a = a+1'b1;

    initial $monitor($time,"a=%b,b=%b,ci=%b | s=%b,co=%b,",a,b,ci,s,co);
    initial #100 $finish;

endmodule

6_adder_4bit/waveform.vcd
$date
	Sun Aug 14 20:09:29 2022
$end
$version
	Icarus Verilog
$end
$timescale
	1ps
$end
$scope module adder_test $end
$var wire 4 ! s [3:0] $end
$var wire 1 " co $end
$var reg 4 # a [3:0] $end
$var reg 4 $ b [3:0] $end
$var reg 1 % ci $end
$scope module uut $end
$var wire 4 & a [3:0] $end
$var wire 4 ' b [3:0] $end
$var wire 1 % ci $end
$var wire 4 ( s [3:0] $end
$var wire 1 " co $end
$var wire 3 ) c [2:0] $end
$scope module add1 $end
$var wire 1 * a $end
$var wire 1 + b $end
$var wire 1 % c $end
$var wire 1 , co $end
$var wire 1 - s $end
$upscope $end
$scope module add2 $end
$var wire 1 . a $end
$var wire 1 / b $end
$var wire 1 0 c $end
$var wire 1 1 co $end
$var wire 1 2 s $end
$upscope $end
$scope module add3 $end
$var wire 1 3 a $end
$var wire 1 4 b $end
$var wire 1 5 c $end
$var wire 1 6 co $end
$var wire 1 7 s $end
$upscope $end
$scope module add4 $end
$var wire 1 8 a $end
$var wire 1 9 b $end
$var wire 1 : c $end
$var wire 1 " co $end
$var wire 1 ; s $end
$upscope $end
$upscope $end
$upscope $end
$enddefinitions $end
#0
$dumpvars
0;
0:
09
08
07
06
05
04
03
02
01
00
0/
0.
0-
0,
0+
0*
b0 )
b0 (
b0 '
b0 &
0%
b0 $
b0 #
0"
b0 !
$end
#1
b1 !
b1 (
1-
1+
b1 $
b1 '
#2
b11 !
b11 (
12
0+
1/
1*
b10 $
b10 '
b1 #
b1 &
#3
17
15
11
02
10
b11 )
1,
b100 !
b100 (
0-
1+
b11 $
b11 '
#4
05
01
0;
12
0:
00
06
b0 )
0,
b110 !
b110 (
17
0+
0/
14
0*
1.
b100 $
b100 '
b10 #
b10 &
#5
b111 !
b111 (
1-
1+
b101 $
b101 '
#6
1;
1:
16
07
15
b110 )
11
b1001 !
b1001 (
02
0+
1/
1*
b110 $
b110 '
b11 #
b11 &
#7
12
10
b111 )
1,
b1010 !
b1010 (
0-
1+
b111 $
b111 '
#8
0:
06
02
17
00
05
0"
0,
b0 )
01
b1100 !
b1100 (
1;
0+
0/
04
19
0*
0.
13
b1000 $
b1000 '
b100 #
b100 &
#9
b1101 !
b1101 (
1-
1+
b1001 $
b1001 '
#10
b1111 !
b1111 (
12
0+
1/
1*
b1010 $
b1010 '
b101 #
b101 &
#11
1"
0;
1:
16
07
15
11
02
10
b111 )
1,
b0 !
b0 (
0-
1+
b1011 $
b1011 '
#12
05
01
12
00
b100 )
0,
b10 !
b10 (
07
0+
0/
14
0*
1.
b1100 $
b1100 '
b110 #
b110 &
#13
b11 !
b11 (
1-
1+
b1101 $
b1101 '
#14
17
15
b110 )
11
b101 !
b101 (
02
0+
1/
1*
b1110 $
b1110 '
b111 #
b111 &
#15
12
10
b111 )
1,
b110 !
b110 (
0-
1+
b1111 $
b1111 '
#16
0"
02
07
b1000 !
b1000 (
1;
00
05
0:
0,
01
b0 )
06
0+
0/
04
09
0*
0.
03
18
b0 $
b0 '
b1000 #
b1000 &
#17
b1001 !
b1001 (
1-
1+
b1 $
b1 '
#18
b1011 !
b1011 (
12
0+
1/
1*
b10 $
b10 '
b1001 #
b1001 &
#19
17
15
11
02
10
b11 )
1,
b1100 !
b1100 (
0-
1+
b11 $
b11 '
#20
05
0"
01
1;
12
0:
00
06
b0 )
0,
b1110 !
b1110 (
17
0+
0/
14
0*
1.
b100 $
b100 '
b1010 #
b1010 &
#21
b1111 !
b1111 (
1-
1+
b101 $
b101 '
#22
1"
0;
1:
16
07
15
b110 )
11
b1 !
b1 (
02
0+
1/
1*
b110 $
b110 '
b1011 #
b1011 &
#23
12
10
b111 )
1,
b10 !
b10 (
0-
1+
b111 $
b111 '
#24
0:
06
02
17
00
05
0,
b0 )
01
b100 !
b100 (
0;
0+
0/
04
19
0*
0.
13
b1000 $
b1000 '
b1100 #
b1100 &
#25
b101 !
b101 (
1-
1+
b1001 $
b1001 '
#26
b111 !
b111 (
12
0+
1/
1*
b1010 $
b1010 '
b1101 #
b1101 &
#27
1;
1:
16
07
15
11
02
10
b111 )
1,
b1000 !
b1000 (
0-
1+
b1011 $
b1011 '
#28
05
01
12
00
b100 )
0,
b1010 !
b1010 (
07
0+
0/
14
0*
1.
b1100 $
b1100 '
b1110 #
b1110 &
#29
b1011 !
b1011 (
1-
1+
b1101 $
b1101 '
#30
17
15
b110 )
11
b1101 !
b1101 (
02
0+
1/
1*
b1110 $
b1110 '
b1111 #
b1111 &
#31
12
10
b111 )
1,
b1110 !
b1110 (
0-
1+
b1111 $
b1111 '
#32
02
07
b0 !
b0 (
0;
00
05
0:
0,
01
b0 )
06
0"
0+
0/
04
09
0*
0.
03
08
b0 $
b0 '
b0 #
b0 &
#33
b1 !
b1 (
1-
1+
b1 $
b1 '
#34
b11 !
b11 (
12
0+
1/
1*
b10 $
b10 '
b1 #
b1 &
#35
17
15
11
02
10
b11 )
1,
b100 !
b100 (
0-
1+
b11 $
b11 '
#36
05
01
0;
12
0:
00
06
b0 )
0,
b110 !
b110 (
17
0+
0/
14
0*
1.
b100 $
b100 '
b10 #
b10 &
#37
b111 !
b111 (
1-
1+
b101 $
b101 '
#38
1;
1:
16
07
15
b110 )
11
b1001 !
b1001 (
02
0+
1/
1*
b110 $
b110 '
b11 #
b11 &
#39
12
10
b111 )
1,
b1010 !
b1010 (
0-
1+
b111 $
b111 '
#40
0:
06
02
17
00
05
0"
0,
b0 )
01
b1100 !
b1100 (
1;
0+
0/
04
19
0*
0.
13
b1000 $
b1000 '
b100 #
b100 &
#41
b1101 !
b1101 (
1-
1+
b1001 $
b1001 '
#42
b1111 !
b1111 (
12
0+
1/
1*
b1010 $
b1010 '
b101 #
b101 &
#43
1"
0;
1:
16
07
15
11
02
10
b111 )
1,
b0 !
b0 (
0-
1+
b1011 $
b1011 '
#44
05
01
12
00
b100 )
0,
b10 !
b10 (
07
0+
0/
14
0*
1.
b1100 $
b1100 '
b110 #
b110 &
#45
b11 !
b11 (
1-
1+
b1101 $
b1101 '
#46
17
15
b110 )
11
b101 !
b101 (
02
0+
1/
1*
b1110 $
b1110 '
b111 #
b111 &
#47
12
10
b111 )
1,
b110 !
b110 (
0-
1+
b1111 $
b1111 '
#48
0"
02
07
b1000 !
b1000 (
1;
00
05
0:
0,
01
b0 )
06
0+
0/
04
09
0*
0.
03
18
b0 $
b0 '
b1000 #
b1000 &
#49
b1001 !
b1001 (
1-
1+
b1 $
b1 '
#50
b1011 !
b1011 (
12
0+
1/
1*
b10 $
b10 '
b1001 #
b1001 &
#51
17
15
11
02
10
b11 )
1,
b1100 !
b1100 (
0-
1+
b11 $
b11 '
#52
05
0"
01
1;
12
0:
00
06
b0 )
0,
b1110 !
b1110 (
17
0+
0/
14
0*
1.
b100 $
b100 '
b1010 #
b1010 &
#53
b1111 !
b1111 (
1-
1+
b101 $
b101 '
#54
1"
0;
1:
16
07
15
b110 )
11
b1 !
b1 (
02
0+
1/
1*
b110 $
b110 '
b1011 #
b1011 &
#55
12
10
b111 )
1,
b10 !
b10 (
0-
1+
b111 $
b111 '
#56
0:
06
02
17
00
05
0,
b0 )
01
b100 !
b100 (
0;
0+
0/
04
19
0*
0.
13
b1000 $
b1000 '
b1100 #
b1100 &
#57
b101 !
b101 (
1-
1+
b1001 $
b1001 '
#58
b111 !
b111 (
12
0+
1/
1*
b1010 $
b1010 '
b1101 #
b1101 &
#59
1;
1:
16
07
15
11
02
10
b111 )
1,
b1000 !
b1000 (
0-
1+
b1011 $
b1011 '
#60
05
01
12
00
b100 )
0,
b1010 !
b1010 (
07
0+
0/
14
0*
1.
b1100 $
b1100 '
b1110 #
b1110 &
#61
b1011 !
b1011 (
1-
1+
b1101 $
b1101 '
#62
17
15
b110 )
11
b1101 !
b1101 (
02
0+
1/
1*
b1110 $
b1110 '
b1111 #
b1111 &
#63
12
10
b111 )
1,
b1110 !
b1110 (
0-
1+
b1111 $
b1111 '
#64
02
07
b0 !
b0 (
0;
00
05
0:
0,
01
b0 )
06
0"
0+
0/
04
09
0*
0.
03
08
b0 $
b0 '
b0 #
b0 &
#65
b1 !
b1 (
1-
1+
b1 $
b1 '
#66
b11 !
b11 (
12
0+
1/
1*
b10 $
b10 '
b1 #
b1 &
#67
17
15
11
02
10
b11 )
1,
b100 !
b100 (
0-
1+
b11 $
b11 '
#68
05
01
0;
12
0:
00
06
b0 )
0,
b110 !
b110 (
17
0+
0/
14
0*
1.
b100 $
b100 '
b10 #
b10 &
#69
b111 !
b111 (
1-
1+
b101 $
b101 '
#70
1;
1:
16
07
15
b110 )
11
b1001 !
b1001 (
02
0+
1/
1*
b110 $
b110 '
b11 #
b11 &
#71
12
10
b111 )
1,
b1010 !
b1010 (
0-
1+
b111 $
b111 '
#72
0:
06
02
17
00
05
0"
0,
b0 )
01
b1100 !
b1100 (
1;
0+
0/
04
19
0*
0.
13
b1000 $
b1000 '
b100 #
b100 &
#73
b1101 !
b1101 (
1-
1+
b1001 $
b1001 '
#74
b1111 !
b1111 (
12
0+
1/
1*
b1010 $
b1010 '
b101 #
b101 &
#75
1"
0;
1:
16
07
15
11
02
10
b111 )
1,
b0 !
b0 (
0-
1+
b1011 $
b1011 '
#76
05
01
12
00
b100 )
0,
b10 !
b10 (
07
0+
0/
14
0*
1.
b1100 $
b1100 '
b110 #
b110 &
#77
b11 !
b11 (
1-
1+
b1101 $
b1101 '
#78
17
15
b110 )
11
b101 !
b101 (
02
0+
1/
1*
b1110 $
b1110 '
b111 #
b111 &
#79
12
10
b111 )
1,
b110 !
b110 (
0-
1+
b1111 $
b1111 '
#80
0"
02
07
b1000 !
b1000 (
1;
00
05
0:
0,
01
b0 )
06
0+
0/
04
09
0*
0.
03
18
b0 $
b0 '
b1000 #
b1000 &
#81
b1001 !
b1001 (
1-
1+
b1 $
b1 '
#82
b1011 !
b1011 (
12
0+
1/
1*
b10 $
b10 '
b1001 #
b1001 &
#83
17
15
11
02
10
b11 )
1,
b1100 !
b1100 (
0-
1+
b11 $
b11 '
#84
05
0"
01
1;
12
0:
00
06
b0 )
0,
b1110 !
b1110 (
17
0+
0/
14
0*
1.
b100 $
b100 '
b1010 #
b1010 &
#85
b1111 !
b1111 (
1-
1+
b101 $
b101 '
#86
1"
0;
1:
16
07
15
b110 )
11
b1 !
b1 (
02
0+
1/
1*
b110 $
b110 '
b1011 #
b1011 &
#87
12
10
b111 )
1,
b10 !
b10 (
0-
1+
b111 $
b111 '
#88
0:
06
02
17
00
05
0,
b0 )
01
b100 !
b100 (
0;
0+
0/
04
19
0*
0.
13
b1000 $
b1000 '
b1100 #
b1100 &
#89
b101 !
b101 (
1-
1+
b1001 $
b1001 '
#90
b111 !
b111 (
12
0+
1/
1*
b1010 $
b1010 '
b1101 #
b1101 &
#91
1;
1:
16
07
15
11
02
10
b111 )
1,
b1000 !
b1000 (
0-
1+
b1011 $
b1011 '
#92
05
01
12
00
b100 )
0,
b1010 !
b1010 (
07
0+
0/
14
0*
1.
b1100 $
b1100 '
b1110 #
b1110 &
#93
b1011 !
b1011 (
1-
1+
b1101 $
b1101 '
#94
17
15
b110 )
11
b1101 !
b1101 (
02
0+
1/
1*
b1110 $
b1110 '
b1111 #
b1111 &
#95
12
10
b111 )
1,
b1110 !
b1110 (
0-
1+
b1111 $
b1111 '
#96
02
07
b0 !
b0 (
0;
00
05
0:
0,
01
b0 )
06
0"
0+
0/
04
09
0*
0.
03
08
b0 $
b0 '
b0 #
b0 &
#97
b1 !
b1 (
1-
1+
b1 $
b1 '
#98
b11 !
b11 (
12
0+
1/
1*
b10 $
b10 '
b1 #
b1 &
#99
17
15
11
02
10
b11 )
1,
b100 !
b100 (
0-
1+
b11 $
b11 '
#100
05
01
0;
12
0:
00
06
b0 )
0,
b110 !
b110 (
17
0+
0/
14
0*
1.
b100 $
b100 '
b10 #
b10 &
