5_full_with_half_adder/half.v
`timescale 1ps/1ps

module half (s,c,a,b);
    input a,b;
    output  s,c;

    assign s=a^b;
    assign c=a&b;
    
endmodule

5_full_with_half_adder/full.v
`timescale 1ps/1ps
`include "half.v"

module full_adder (s,co,a,b,ci);

    input a,b,ci;
    output s,co;

    wire t,k;

    half v1(t,c,a,b);
    half v2(s,k,t,ci);
    or(co,k,c);
endmodule

5_full_with_half_adder/full_test.v
`timescale 1ps/1ps
`include "full.v"


module full_test;

    reg a;
    reg b;
    reg ci;

    wire s;
    wire co;

    full_adder uut(
        .s(s),
        .co(co),
        .a(a),
        .b(b),
        .ci(ci)
    );

    initial begin
        $dumpfile("waveform.vcd");
        $dumpvars(0,full_test);

        a = 1'b0;
        b = 1'b0;
        ci = 1'b0;
    end

    always #4 a=a+1'b1;
    always #2 b=b+1'b1;
    always #1 ci=ci+1'b1;

    initial $monitor($time,"a=%b,b=%b,ci=%b | s=%b,co=%b,",a,b,ci,s,co);
    initial #100 $finish;

endmodule

5_full_with_half_adder/waveform.vcd
$date
	Sun Aug 14 18:32:26 2022
$end
$version
	Icarus Verilog
$end
$timescale
	1ps
$end
$scope module full_test $end
$var wire 1 ! s $end
$var wire 1 " co $end
$var reg 1 # a $end
$var reg 1 $ b $end
$var reg 1 % ci $end
$scope module uut $end
$var wire 1 # a $end
$var wire 1 $ b $end
$var wire 1 % ci $end
$var wire 1 " co $end
$var wire 1 & t $end
$var wire 1 ! s $end
$var wire 1 ' k $end
$var wire 1 ( c $end
$scope module v1 $end
$var wire 1 # a $end
$var wire 1 $ b $end
$var wire 1 ( c $end
$var wire 1 & s $end
$upscope $end
$scope module v2 $end
$var wire 1 & a $end
$var wire 1 % b $end
$var wire 1 ' c $end
$var wire 1 ! s $end
$upscope $end
$upscope $end
$upscope $end
$enddefinitions $end
#0
$dumpvars
0(
0'
0&
0%
0$
0#
0"
0!
$end
#1
1!
1%
#2
1&
0%
1$
#3
1"
0!
1'
1%
#4
0"
1!
0'
0%
0$
1#
#5
1"
0!
1'
1%
#6
0'
0&
1(
0%
1$
#7
1!
1%
#8
0"
0!
0(
0%
0$
0#
#9
1!
1%
#10
1&
0%
1$
#11
1"
0!
1'
1%
#12
0"
1!
0'
0%
0$
1#
#13
1"
0!
1'
1%
#14
0'
0&
1(
0%
1$
#15
1!
1%
#16
0"
0!
0(
0%
0$
0#
#17
1!
1%
#18
1&
0%
1$
#19
1"
0!
1'
1%
#20
0"
1!
0'
0%
0$
1#
#21
1"
0!
1'
1%
#22
0'
0&
1(
0%
1$
#23
1!
1%
#24
0"
0!
0(
0%
0$
0#
#25
1!
1%
#26
1&
0%
1$
#27
1"
0!
1'
1%
#28
0"
1!
0'
0%
0$
1#
#29
1"
0!
1'
1%
#30
0'
0&
1(
0%
1$
#31
1!
1%
#32
0"
0!
0(
0%
0$
0#
#33
1!
1%
#34
1&
0%
1$
#35
1"
0!
1'
1%
#36
0"
1!
0'
0%
0$
1#
#37
1"
0!
1'
1%
#38
0'
0&
1(
0%
1$
#39
1!
1%
#40
0"
0!
0(
0%
0$
0#
#41
1!
1%
#42
1&
0%
1$
#43
1"
0!
1'
1%
#44
0"
1!
0'
0%
0$
1#
#45
1"
0!
1'
1%
#46
0'
0&
1(
0%
1$
#47
1!
1%
#48
0"
0!
0(
0%
0$
0#
#49
1!
1%
#50
1&
0%
1$
#51
1"
0!
1'
1%
#52
0"
1!
0'
0%
0$
1#
#53
1"
0!
1'
1%
#54
0'
0&
1(
0%
1$
#55
1!
1%
#56
0"
0!
0(
0%
0$
0#
#57
1!
1%
#58
1&
0%
1$
#59
1"
0!
1'
1%
#60
0"
1!
0'
0%
0$
1#
#61
1"
0!
1'
1%
#62
0'
0&
1(
0%
1$
#63
1!
1%
#64
0"
0!
0(
0%
0$
0#
#65
1!
1%
#66
1&
0%
1$
#67
1"
0!
1'
1%
#68
0"
1!
0'
0%
0$
1#
#69
1"
0!
1'
1%
#70
0'
0&
1(
0%
1$
#71
1!
1%
#72
0"
0!
0(
0%
0$
0#
#73
1!
1%
#74
1&
0%
1$
#75
1"
0!
1'
1%
#76
0"
1!
0'
0%
0$
1#
#77
1"
0!
1'
1%
#78
0'
0&
1(
0%
1$
#79
1!
1%
#80
0"
0!
0(
0%
0$
0#
#81
1!
1%
#82
1&
0%
1$
#83
1"
0!
1'
1%
#84
0"
1!
0'
0%
0$
1#
#85
1"
0!
1'
1%
#86
0'
0&
1(
0%
1$
#87
1!
1%
#88
0"
0!
0(
0%
0$
0#
#89
1!
1%
#90
1&
0%
1$
#91
1"
0!
1'
1%
#92
0"
1!
0'
0%
0$
1#
#93
1"
0!
1'
1%
#94
0'
0&
1(
0%
1$
#95
1!
1%
#96
0"
0!
0(
0%
0$
0#
#97
1!
1%
#98
1&
0%
1$
#99
1"
0!
1'
1%
#100
0"
1!
0'
0%
0$
1#
