4_full_subtractor/behavioral/full_subtractor.v
`timescale 1ps/1ps

module full_subtractor (
    d,
    bo,
    a,
    b,
    bi
);

    input a,b,bi;
    output reg d,bo;

    always @(*) begin
       d = a^b^bi;
       bo = ((~a)&b)|(~(a^b)&bi);
    end
    
endmodule

4_full_subtractor/structural/full_subtractor_test.v
`timescale 1ps/1ps
`include "full_subtractor.v"

module full_subtractor_test;

    // input
    reg a;
    reg b;
    reg bi;

    // output
    wire d;
    wire bo;

    // instantiate
    full_subtractor uut (
        .d(d),
        .bo(bo),
        .a(a),
        .b(b),
        .bi(bi)
    );

    initial begin
        $dumpfile("waveform.vcd");
        $dumpvars(0,full_subtractor_test);
        
        a = 1'b0;
        b = 1'b0;
        bi = 1'b0;
    end
    
    always #4 a=a+1'b1;
    always #2 b=b+1'b1;
    always #1 bi=bi+1'b1;
    

    initial $monitor("d=%b,bo=%b,a=%b,b=%b,bi=%b",d,bo,a,b,bi);
    initial #20 $finish;
endmodule

full_subtractor/behavioral/waveform.vcd
$date
	Sun Aug 14 16:56:39 2022
$end
$version
	Icarus Verilog
$end
$timescale
	1ps
$end
$scope module full_subtractor_test $end
$var wire 1 ! d $end
$var wire 1 " bo $end
$var reg 1 # a $end
$var reg 1 $ b $end
$var reg 1 % bi $end
$scope module uut $end
$var wire 1 # a $end
$var wire 1 $ b $end
$var wire 1 % bi $end
$var reg 1 " bo $end
$var reg 1 ! d $end
$upscope $end
$upscope $end
$enddefinitions $end
#0
$dumpvars
0%
0$
0#
0"
0!
$end
#1
1"
1!
1%
#2
0%
1$
#3
0!
1%
#4
0"
1!
0%
0$
1#
#5
0!
1%
#6
0%
1$
#7
1"
1!
1%
#8
0"
0!
0%
0$
0#
#9
1"
1!
1%
#10
0%
1$
#11
0!
1%
#12
0"
1!
0%
0$
1#
#13
0!
1%
#14
0%
1$
#15
1"
1!
1%
#16
0"
0!
0%
0$
0#
#17
1"
1!
1%
#18
0%
1$
#19
0!
1%
#20
0"
1!
0%
0$
1#
