Test/d_flipflop.v
`timescale 1ps/1ps

module d_flipflop (
    output reg q,
    input d, clk, clear
);
    always @(posedge clk or negedge clear) begin
        if (clear==1'b0)
            begin q<=1'b0; end
        else 
            begin q<=d; end
    end
    
endmodule

assignment_1/Q2/lfsr.v
`timescale 1ps/1ps
`include "d_flipflop.v"

module lfsr (state,seed,clk,reset);
    output [15:0] state;
    input [15:0] seed;
    input clk, reset;

    reg [10:0] r1,c1;
    reg [1:0] r2,r4,c2,c4;
    reg r3,c3;
    wire w1,w2,w3,w4;

    reg flag=1'b1;

    always @(posedge clk, negedge reset) begin

        if (~reset) begin 
            r1=11'b00000000000;
            r2=2'b00;
            r3=1'b0;
            r4=2'b00;
        end else begin 
            if(flag) begin
                r1=seed[10:0];
                r2=seed[12:11];
                r3=seed[13];
                r4=seed[15:14];

                flag=1'b0;
            end else begin 
                r1=c1;
                r2=c2;
                r3=c3;
                r4=c4;
            end
        end
    end

    always @(w1, r1) begin
        c1 = {w1,r1[10:1]};
    end

    always @(w2, r2) begin
        c2 = {w2,r2[1]};
    end

    always @(w3, r3) begin
        c3 = w3;
    end

    always @(w4, r4) begin
        c4 = {w4,r4[1]};
    end



    assign w1 = r1[0]^r2[0];
    assign w2 = r1[0]^r3;
    assign w3 = r1[0]^r4[0];
    assign w4 = r1[0];


    d_flipflop d1(state[0],r1[0],clk,reset);
    d_flipflop d2(state[1],r1[1],clk,reset);
    d_flipflop d3(state[2],r1[2],clk,reset);
    d_flipflop d4(state[3],r1[3],clk,reset);
    d_flipflop d5(state[4],r1[4],clk,reset);
    d_flipflop d6(state[5],r1[5],clk,reset);
    d_flipflop d7(state[6],r1[6],clk,reset);
    d_flipflop d8(state[7],r1[7],clk,reset);
    d_flipflop d9(state[8],r1[8],clk,reset);
    d_flipflop d10(state[9],r1[9],clk,reset);
    d_flipflop d11(state[10],r1[10],clk,reset);

    d_flipflop d12(state[11],r2[0],clk,reset);
    d_flipflop d13(state[12],r2[1],clk,reset);
    
    d_flipflop d14(state[13],r3,clk,reset);
    
    d_flipflop d15(state[14],r4[0],clk,reset);
    d_flipflop d16(state[15],r4[1],clk,reset);
    
endmodule

assignment_1/Q2/lfsr_test.v
`timescale 1ps/1ps
`include "lfsr.v"

module lfsr_test;
    reg[15:0] seed;
    reg clk;
    reg reset;

    wire[15:0] state;


    lfsr uut(
        .state(state),
        .seed(seed),
        .clk(clk),
        .reset(reset)
    );

    initial begin
        $dumpfile("waveform.vcd");
        $dumpvars(0,lfsr_test);
        
        seed = 16'b1010110011100001;
        clk=1'b0;
        reset=1'b1;
    end

    always #1 clk=!clk;
    initial #90 reset=1'b0;

    initial $monitor($time," clk=%b, reset=%b,seed=%b | state=%b ",clk,reset,seed,state);
    initial #100 $finish;
    

endmodule

assignment_1/Q2/waveform.vcd
$date
	Tue Aug 16 16:40:52 2022
$end
$version
	Icarus Verilog
$end
$timescale
	1ps
$end
$scope module lfsr_test $end
$var wire 16 ! state [15:0] $end
$var reg 1 " clk $end
$var reg 1 # reset $end
$var reg 16 $ seed [15:0] $end
$scope module uut $end
$var wire 1 " clk $end
$var wire 1 # reset $end
$var wire 16 % seed [15:0] $end
$var wire 1 & w1 $end
$var wire 1 ' w2 $end
$var wire 1 ( w3 $end
$var wire 1 ) w4 $end
$var wire 16 * state [15:0] $end
$var reg 11 + c1 [10:0] $end
$var reg 2 , c2 [1:0] $end
$var reg 1 - c3 $end
$var reg 2 . c4 [1:0] $end
$var reg 1 / flag $end
$var reg 11 0 r1 [10:0] $end
$var reg 2 1 r2 [1:0] $end
$var reg 1 2 r3 $end
$var reg 2 3 r4 [1:0] $end
$scope module d1 $end
$var wire 1 # clear $end
$var wire 1 " clk $end
$var wire 1 4 d $end
$var reg 1 5 q $end
$upscope $end
$scope module d10 $end
$var wire 1 # clear $end
$var wire 1 " clk $end
$var wire 1 6 d $end
$var reg 1 7 q $end
$upscope $end
$scope module d11 $end
$var wire 1 # clear $end
$var wire 1 " clk $end
$var wire 1 8 d $end
$var reg 1 9 q $end
$upscope $end
$scope module d12 $end
$var wire 1 # clear $end
$var wire 1 " clk $end
$var wire 1 : d $end
$var reg 1 ; q $end
$upscope $end
$scope module d13 $end
$var wire 1 # clear $end
$var wire 1 " clk $end
$var wire 1 < d $end
$var reg 1 = q $end
$upscope $end
$scope module d14 $end
$var wire 1 # clear $end
$var wire 1 " clk $end
$var wire 1 2 d $end
$var reg 1 > q $end
$upscope $end
$scope module d15 $end
$var wire 1 # clear $end
$var wire 1 " clk $end
$var wire 1 ? d $end
$var reg 1 @ q $end
$upscope $end
$scope module d16 $end
$var wire 1 # clear $end
$var wire 1 " clk $end
$var wire 1 A d $end
$var reg 1 B q $end
$upscope $end
$scope module d2 $end
$var wire 1 # clear $end
$var wire 1 " clk $end
$var wire 1 C d $end
$var reg 1 D q $end
$upscope $end
$scope module d3 $end
$var wire 1 # clear $end
$var wire 1 " clk $end
$var wire 1 E d $end
$var reg 1 F q $end
$upscope $end
$scope module d4 $end
$var wire 1 # clear $end
$var wire 1 " clk $end
$var wire 1 G d $end
$var reg 1 H q $end
$upscope $end
$scope module d5 $end
$var wire 1 # clear $end
$var wire 1 " clk $end
$var wire 1 I d $end
$var reg 1 J q $end
$upscope $end
$scope module d6 $end
$var wire 1 # clear $end
$var wire 1 " clk $end
$var wire 1 K d $end
$var reg 1 L q $end
$upscope $end
$scope module d7 $end
$var wire 1 # clear $end
$var wire 1 " clk $end
$var wire 1 M d $end
$var reg 1 N q $end
$upscope $end
$scope module d8 $end
$var wire 1 # clear $end
$var wire 1 " clk $end
$var wire 1 O d $end
$var reg 1 P q $end
$upscope $end
$scope module d9 $end
$var wire 1 # clear $end
$var wire 1 " clk $end
$var wire 1 Q d $end
$var reg 1 R q $end
$upscope $end
$upscope $end
$upscope $end
$enddefinitions $end
#0
$dumpvars
xR
xQ
xP
xO
xN
xM
xL
xK
xJ
xI
xH
xG
xF
xE
xD
xC
xB
xA
x@
x?
x>
x=
x<
x;
x:
x9
x8
x7
x6
x5
x4
bx 3
x2
bx 1
bx 0
1/
bx .
x-
bx ,
bx +
bx *
x)
x(
x'
x&
b1010110011100001 %
b1010110011100001 $
1#
0"
bx !
$end
#1
bx1xxxxxxxxxxxxx !
bx1xxxxxxxxxxxxx *
1>
1-
0&
1(
b11 .
0?
1A
0'
b0 ,
1:
0<
b1001110000 +
1)
14
0C
0E
0G
0I
1K
1M
1O
0Q
06
18
0/
b10 3
12
b1 1
b10011100001 0
1"
#2
0"
#3
1B
0@
0=
1;
19
07
0R
1P
1N
1L
0J
0H
0F
0D
b1010110011100001 !
b1010110011100001 *
15
b10 ,
1'
b1 .
1?
0:
b100111000 +
0)
04
1I
0O
16
08
b11 3
b0 1
b1001110000 0
1"
#4
0"
#5
05
1J
0P
17
09
0;
b1110001001110000 !
b1110001001110000 *
1@
b0 .
0A
b11 ,
1<
b10011100 +
1G
0M
1Q
06
b1 3
b10 1
b100111000 0
1"
#6
0"
#7
0B
1=
07
1R
0N
b111000100111000 !
b111000100111000 *
1H
0-
0(
1&
0?
1:
b10001001110 +
1E
0K
1O
0Q
b0 3
b11 1
b10011100 0
1"
#8
0"
#9
1F
0L
1P
0R
1;
0>
b1100010011100 !
b1100010011100 *
0@
b1 ,
0'
b11000100111 +
1C
0I
1M
0O
18
02
b10001001110 0
1"
#10
0"
#11
19
0P
1N
0J
b1110001001110 !
b1110001001110 *
1D
1-
0&
1'
1(
b10 .
b10 ,
0<
b1100010011 +
1)
14
0G
1K
0M
16
b1 1
b11000100111 0
1"
#12
0"
#13
15
0H
1L
0N
17
0=
b10111000100111 !
b10111000100111 *
1>
1&
b11 .
1A
0'
b1 ,
0:
1<
b10110001001 +
0E
1I
0K
1Q
08
b10 3
12
b10 1
b1100010011 0
1"
#14
0"
#15
1B
1=
0;
09
1R
0L
1J
b1011001100010011 !
b1011001100010011 *
0F
0-
0(
0&
1?
b0 ,
1:
0<
b1011000100 +
0C
1G
0I
1O
06
18
b11 3
b1 1
b10110001001 0
1"
#16
0"
#17
0D
1H
0J
1P
07
19
1;
0=
0>
b1100110110001001 !
b1100110110001001 *
1@
1-
1(
b1 .
0:
b101100010 +
0)
04
1E
0G
1M
0Q
16
08
02
b0 1
b1011000100 0
1"
#18
0"
#19
0;
09
17
0R
1N
0H
1F
b1100001011000100 !
b1100001011000100 *
05
b10 ,
b0 .
0A
1'
b10110001 +
1C
0E
1K
0O
1Q
06
b1 3
12
b101100010 0
1"
#20
0"
#21
1D
0F
1L
0P
1R
07
1>
b110000101100010 !
b110000101100010 *
0B
1&
0'
b10 .
0?
b1 ,
1<
b10001011000 +
1)
14
0C
1I
0M
1O
0Q
b0 3
b10 1
b10110001 0
1"
#22
0"
#23
0@
1=
0R
1P
0N
1J
0D
b11000010110001 !
b11000010110001 *
15
0-
1'
0(
b1 .
1A
b10 ,
1:
0<
b11000101100 +
0)
04
1G
0K
1M
0O
18
b10 3
b1 1
b10001011000 0
1"
#24
0"
#25
05
1H
0L
1N
0P
19
1;
0=
0>
b1000110001011000 !
b1000110001011000 *
1B
1-
1(
0&
b0 .
1?
0A
0'
b1 ,
0:
1<
b1100010110 +
1E
0I
1K
0M
16
b1 3
02
b10 1
b11000101100 0
1"
#26
0"
#27
0B
1@
1=
0;
17
0N
1L
0J
b101011000101100 !
b101011000101100 *
1F
0-
0(
1&
0?
1'
b10 ,
1:
0<
b10110001011 +
1C
0G
1I
0K
1Q
08
b0 3
12
b1 1
b1100010110 0
1"
#28
0"
#29
1D
0H
1J
0L
1R
09
1;
0=
b101100010110 !
b101100010110 *
0@
1-
1(
b10 .
b11 ,
0:
1<
b11011000101 +
1)
14
0E
1G
0I
1O
06
18
02
b10 1
b10110001011 0
1"
#30
0"
#31
1=
0;
19
07
1P
0J
1H
0F
b1010110001011 !
b1010110001011 *
15
b1 ,
0&
b11 .
1A
0'
1:
b1101100010 +
0C
1E
0G
1M
0Q
16
b10 3
12
b11 1
b11011000101 0
1"
#32
0"
#33
0D
1F
0H
1N
0R
17
1;
1>
b1011111011000101 !
b1011111011000101 *
1B
1&
1'
b1 .
1?
b10 ,
0<
b10110110001 +
0)
04
1C
0E
1K
0O
1Q
08
b11 3
b1 1
b1101100010 0
1"
#34
0"
#35
1@
0=
09
1R
0P
1L
0F
1D
b1110101101100010 !
b1110101101100010 *
05
0-
0'
0(
b10 .
0A
b1 ,
0:
1<
b11011011000 +
1)
14
0C
1I
0M
1O
06
18
b1 3
b10 1
b10110110001 0
1"
#36
0"
#37
15
0D
1J
0N
1P
07
19
0;
1=
0>
b101010110110001 !
b101010110110001 *
0B
b1 .
0?
1A
b0 ,
1:
0<
b11101101100 +
0)
04
1G
0K
1M
0Q
16
b10 3
02
b1 1
b11011011000 0
1"
#38
0"
#39
1B
0@
0=
1;
17
0R
1N
0L
1H
b1000111011011000 !
b1000111011011000 *
05
1-
1(
0&
b0 .
1?
0A
0:
b1110110110 +
1E
0I
1K
0O
1Q
b1 3
b0 1
b11101101100 0
1"
#40
0"
#41
1F
0J
1L
0P
1R
0;
1>
1@
b110011101101100 !
b110011101101100 *
0B
0-
0(
b10 ,
0?
1'
b111011011 +
1C
0G
1I
0M
1O
08
b0 3
12
b1110110110 0
1"
#42
0"
#43
0@
09
1P
0N
1J
0H
b10001110110110 !
b10001110110110 *
1D
1-
1&
1(
b10 .
b11 ,
1<
b10011101101 +
1)
14
0E
1G
0K
1M
06
02
b10 1
b111011011 0
1"
#44
0"
#45
15
0F
1H
0L
1N
07
b11000111011011 !
b11000111011011 *
1=
b1 ,
0&
b11 .
1A
0'
1:
b1001110110 +
0C
1E
0I
1K
0Q
18
b10 3
12
b11 1
b10011101101 0
1"
#46
0"
#47
1B
1;
19
0R
1L
0J
1F
b1011110011101101 !
b1011110011101101 *
0D
1&
1'
b1 .
1?
b10 ,
0<
b10100111011 +
0)
04
1C
0G
1I
0O
16
08
b11 3
b1 1
b1001110110 0
1"
#48
0"
#49
05
1D
0H
1J
0P
17
09
0=
b1110101001110110 !
b1110101001110110 *
1@
0-
0'
0(
b10 .
0A
b1 ,
0:
1<
b11010011101 +
1)
14
0E
1G
0M
1Q
06
18
b1 3
b10 1
b10100111011 0
1"
#50
0"
#51
0B
1=
0;
19
07
1R
0N
1H
0F
b111010100111011 !
b111010100111011 *
15
1-
1(
0&
b11 .
0?
1A
1'
b10 ,
1:
0<
b1101001110 +
0C
1E
0K
1O
0Q
16
b10 3
02
b1 1
b11010011101 0
1"
#52
0"
#53
0D
1F
0L
1P
0R
17
1;
0=
0@
b1010111010011101 !
b1010111010011101 *
1B
b1 .
1?
b11 ,
0:
1<
b110100111 +
0)
04
1C
0I
1M
0O
1Q
08
b11 3
12
b10 1
b1101001110 0
1"
#54
0"
#55
1@
1=
0;
09
1R
0P
1N
0J
1D
b1111001101001110 !
b1111001101001110 *
05
b1 ,
0-
0'
0(
b10 .
0A
1:
b11010011 +
1)
14
0G
1K
0M
1O
06
b1 3
b11 1
b110100111 0
1"
#56
0"
#57
15
0H
1L
0N
1P
07
1;
0>
b101100110100111 !
b101100110100111 *
0B
1-
1(
b11 .
0?
1A
1'
b10 ,
0<
b1101001 +
0E
1I
0K
1M
0Q
b10 3
02
b1 1
b11010011 0
1"
#58
0"
#59
1B
0@
0=
0R
1N
0L
1J
b1000100011010011 !
b1000100011010011 *
0F
0-
0(
1&
1?
0'
b1 ,
0:
1<
b10000110100 +
0C
1G
0I
1K
0O
b11 3
12
b10 1
b1101001 0
1"
#60
0"
#61
0D
1H
0J
1L
0P
0;
1=
b1101000001101001 !
b1101000001101001 *
1@
1-
1(
b1 .
b0 ,
1:
0<
b11000011010 +
0)
04
1E
0G
1I
0M
18
02
b1 1
b10000110100 0
1"
#62
0"
#63
0=
1;
19
0N
1J
0H
1F
b1100110000110100 !
b1100110000110100 *
05
b10 ,
0&
b0 .
0A
1'
0:
b1100001101 +
1C
0E
1G
0K
16
b1 3
12
b0 1
b11000011010 0
1"
#64
0"
#65
1D
0F
1H
0L
17
0;
1>
b110011000011010 !
b110011000011010 *
0B
1&
0'
b10 .
0?
b1 ,
1<
b10110000110 +
1)
14
0C
1E
0I
1Q
08
b0 3
b10 1
b1100001101 0
1"
#66
0"
#67
0@
1=
09
1R
0J
1F
0D
b11001100001101 !
b11001100001101 *
15
0-
1'
0(
b1 .
1A
b10 ,
1:
0<
b11011000011 +
0)
04
1C
0G
1O
06
18
b10 3
b1 1
b10110000110 0
1"
#68
0"
#69
05
1D
0H
1P
07
19
1;
0=
0>
b1000110110000110 !
b1000110110000110 *
1B
b10 .
1?
0A
b11 ,
0:
1<
b11101100001 +
1)
14
0E
1M
0Q
16
b1 3
02
b10 1
b11011000011 0
1"
#70
0"
#71
0B
1@
1=
0;
17
0R
1N
0F
b101011011000011 !
b101011011000011 *
15
1-
1(
0&
b11 .
0?
1A
1:
b1110110000 +
0C
1K
0O
1Q
b10 3
b11 1
b11101100001 0
1"
#72
0"
#73
0D
1L
0P
1R
1;
1>
0@
b1011111101100001 !
b1011111101100001 *
1B
1&
b1 .
1?
b10111011000 +
0)
04
1I
0M
1O
08
b11 3
12
b1110110000 0
1"
#74
0"
#75
1@
09
1P
0N
1J
b1111101110110000 !
b1111101110110000 *
05
b0 .
0A
b11011101100 +
1G
0K
1M
06
18
b1 3
b10111011000 0
1"
#76
0"
#77
1H
0L
1N
07
19
b111110111011000 !
b111110111011000 *
0B
0-
0(
0?
b11101110110 +
1E
0I
1K
0Q
16
b0 3
b11011101100 0
1"
#78
0"
#79
0@
17
0R
1L
0J
b11111011101100 !
b11111011101100 *
1F
b1 ,
0'
b11110111011 +
1C
0G
1I
0O
1Q
02
b11101110110 0
1"
#80
0"
#81
1D
0H
1J
0P
1R
b1111101110110 !
b1111101110110 *
0>
1-
0&
1'
1(
b10 .
b10 ,
0<
b1111011101 +
1)
14
0E
1G
0M
1O
b1 1
b11110111011 0
1"
#82
0"
#83
0=
1P
0N
1H
0F
b111110111011 !
b111110111011 *
15
1&
b11 .
1A
0'
b1 ,
0:
1<
b10111101110 +
0C
1E
0K
1M
08
b10 3
12
b10 1
b1111011101 0
1"
#84
0"
#85
0D
1F
0L
1N
09
0;
1=
1>
b1011001111011101 !
b1011001111011101 *
1B
1'
b1 .
1?
b10 ,
1:
0<
b11011110111 +
0)
04
1C
0I
1K
06
18
b11 3
b1 1
b10111101110 0
1"
#86
0"
#87
1@
0=
1;
19
07
1L
0J
1D
b1110110111101110 !
b1110110111101110 *
05
0-
0'
0(
b10 .
0A
b1 ,
0:
1<
b11101111011 +
1)
14
0G
1I
0Q
16
b1 3
b10 1
b11011110111 0
1"
#88
0"
#89
15
0H
1J
0R
17
0;
1=
0>
b101011011110111 !
b101011011110111 *
0B
1-
1(
0&
b11 .
0?
1A
1'
b10 ,
1:
0<
b1110111101 +
0E
1G
0O
1Q
b10 3
02
b1 1
b11101111011 0
1"
#90
0@
0=
09
07
0P
0N
0L
0J
0F
0D
b0 !
b0 *
05
b0 ,
0-
0'
0(
b0 .
0A
0:
b0 +
0)
04
0C
0G
0I
0K
0M
0Q
06
08
b0 3
b0 1
b0 0
0"
0#
