10_FSM/RGY/cyclic_lamp.v
`timescale 1ps/1ps

module cyclic_lamp (
    clock,light
);
    input clock;
    output reg[0:2] light;
    parameter s0 = 0, s1 = 1, s2 = 2 ;
    parameter RED=3'b100, GREEN=3'b010, YELLOW=3'b001;
    reg [0:1] state;

    always @(posedge clock ) begin
        case (state)
            s0: state<=s1;
            s1: state<=s2;
            s2: state<=s0;
            default: state<=s0;
        endcase
    end

    always @(state) begin
        case (state)
            s0: light=RED;
            s1: light=GREEN;
            s2: light=YELLOW;
            default: light=RED;
        endcase
    end

endmodule

10_FSM/RGY/cyclic_lamp_test.v
`timescale 1ps/1ps
`include "cyclic_lamp.v"

module cyclic_lamp_test;
    reg clock;
    wire [0:2] light;

    cyclic_lamp LAMP (clock,light);

    initial begin
        $dumpfile("waveform.vcd");
        $dumpvars(0,cyclic_lamp_test);

        clock=1'b0;
        #100 $finish;
    end

    always #5 clock=~clock;
    initial $monitor($time," RGY = %b ", light);


endmodule

10_FSM/RGY/waveform.vcd
$date
	Sat Sep  3 21:23:36 2022
$end
$version
	Icarus Verilog
$end
$timescale
	1ps
$end
$scope module cyclic_lamp_test $end
$var wire 3 ! light [0:2] $end
$var reg 1 " clock $end
$scope module LAMP $end
$var wire 1 " clock $end
$var reg 3 # light [0:2] $end
$var reg 2 $ state [0:1] $end
$upscope $end
$upscope $end
$enddefinitions $end
#0
$dumpvars
bx $
bx #
0"
bx !
$end
#5
b100 !
b100 #
b0 $
1"
#10
0"
#15
b10 !
b10 #
b1 $
1"
#20
0"
#25
b1 !
b1 #
b10 $
1"
#30
0"
#35
b100 !
b100 #
b0 $
1"
#40
0"
#45
b10 !
b10 #
b1 $
1"
#50
0"
#55
b1 !
b1 #
b10 $
1"
#60
0"
#65
b100 !
b100 #
b0 $
1"
#70
0"
#75
b10 !
b10 #
b1 $
1"
#80
0"
#85
b1 !
b1 #
b10 $
1"
#90
0"
#95
b100 !
b100 #
b0 $
1"
