assignment_2/Q1/extended_euclidean.v
`timescale 1ps/1ps

module extended_euclidean (
    a_inverse, prime, a, clk
);
    output [7:0] a_inverse;
    input[7:0] prime, a;
    input clk;

    reg[7:0] A, B, quotient, remainder, T, result;
    reg[7:0] T1=8'b00000000;
    reg[7:0] T2=8'b00000001;

    // Set of all states of FSM
    reg [2:0] state;
    parameter load = 0;
    parameter compute_QR = 1;
    parameter compute_T = 2;
    parameter shift = 3;
    parameter complete = 4;


    assign a_inverse = result;



    // State transition of FSM
    always @(posedge clk ) begin 
        case(state)
            load: state <= compute_QR;
            
            compute_QR: state <= compute_T;
            
            compute_T: state <= shift;
            
            shift: 
                begin 
                    if (A == 0) 
                        state <= complete;
                    else
                        state <= compute_QR;
                end
            
            complete: state <= complete;
            
            default: state <= load;
        endcase
    end



    // State operations of FSM
    always @(state) begin 
        case(state)
            load:
                begin 
                    B = prime;
                    A = a;
                end

            compute_QR: 
                begin 
                    quotient = B / A;
                    remainder = B % A;
                end
            
            compute_T: T = T1-(T2*quotient); 
            
            shift: 
                begin 
                    B = A;
                    A = remainder;
                    T1 = T2;
                    T2 = T;
                end
            
            complete: result = T1;
        endcase
    end
    
endmodule

assignment_2/Q1/extended_euclidean_test.v
`timescale 1ps/1ps
`include "extended_euclidean.v"

module extended_euclidean_test;
    reg[7:0] prime, a;
    reg clk;

    wire[7:0] a_inverse;

    extended_euclidean uut (
        .a_inverse(a_inverse),
        .prime(prime),
        .a(a),
        .clk(clk)
    );

    initial begin 
        $dumpfile("waveform.vcd");
        $dumpvars(0,extended_euclidean_test);

        clk=1'b0;

        prime=8'b00000101;
        a=8'b00000011;

        // prime=8'b00001101;
        // a=8'b00001011;
    end


    initial $monitor(" clk=%b, prime=%b, a=%b | a_inverse=%b ", clk, prime, a, a_inverse);
    always #1 clk=!clk;
    initial #30 $finish;


endmodule

assignment_2/Q1/waveform.vcd
$date
	Sun Sep  4 02:49:55 2022
$end
$version
	Icarus Verilog
$end
$timescale
	1ps
$end
$scope module extended_euclidean_test $end
$var wire 8 ! a_inverse [7:0] $end
$var reg 8 " a [7:0] $end
$var reg 1 # clk $end
$var reg 8 $ prime [7:0] $end
$scope module uut $end
$var wire 8 % a [7:0] $end
$var wire 8 & a_inverse [7:0] $end
$var wire 1 # clk $end
$var wire 8 ' prime [7:0] $end
$var reg 8 ( A [7:0] $end
$var reg 8 ) B [7:0] $end
$var reg 8 * T [7:0] $end
$var reg 8 + T1 [7:0] $end
$var reg 8 , T2 [7:0] $end
$var reg 8 - quotient [7:0] $end
$var reg 8 . remainder [7:0] $end
$var reg 8 / result [7:0] $end
$var reg 3 0 state [2:0] $end
$upscope $end
$upscope $end
$enddefinitions $end
#0
$dumpvars
bx 0
bx /
bx .
bx -
b1 ,
b0 +
bx *
bx )
bx (
b101 '
bx &
b11 %
b101 $
0#
b11 "
bx !
$end
#1
b11 (
b101 )
b0 0
1#
#2
0#
#3
b10 .
b1 -
b1 0
1#
#4
0#
#5
b11111111 *
b10 0
1#
#6
0#
#7
b11111111 ,
b1 +
b10 (
b11 )
b11 0
1#
#8
0#
#9
b1 .
b1 0
1#
#10
0#
#11
b10 *
b10 0
1#
#12
0#
#13
b10 ,
b11111111 +
b1 (
b10 )
b11 0
1#
#14
0#
#15
b0 .
b10 -
b1 0
1#
#16
0#
#17
b11111011 *
b10 0
1#
#18
0#
#19
b11111011 ,
b10 +
b0 (
b1 )
b11 0
1#
#20
0#
#21
b10 !
b10 &
b10 /
b100 0
1#
